alice_lri/__init__.py
alice_lri/_alice_lri.cpython-313t-x86_64-linux-gnu.so
alice_lri/_alice_lri.pyi
alice_lri/libalice_lri.so
alice_lri/libalice_lri.so.0
alice_lri/libalice_lri.so.0.1.0
alice_lri-0.1.0.dist-info/METADATA
alice_lri-0.1.0.dist-info/WHEEL
alice_lri-0.1.0.dist-info/RECORD
