Metadata-Version: 2.2
Name: alice-lri
Version: 0.1.0
Summary: LiDAR Range Image processing and intrinsic parameter estimation library
Keywords: lidar,range-image,point-cloud,computer-vision,robotics
Author-Email: Samuel Soutullo <s.soutullo@usc.es>
License: MIT
Classifier: Development Status :: 4 - Beta
Classifier: Intended Audience :: Science/Research
Classifier: Intended Audience :: Developers
Classifier: Topic :: Scientific/Engineering
Classifier: Topic :: Software Development :: Libraries :: Python Modules
Classifier: Programming Language :: Python :: 3.8
Classifier: Programming Language :: Python :: 3.9
Classifier: Programming Language :: Python :: 3.10
Classifier: Programming Language :: Python :: 3.11
Classifier: Programming Language :: Python :: 3.12
Classifier: Programming Language :: Python :: 3.13
Classifier: Programming Language :: Python :: 3.14
Classifier: Programming Language :: C++
Classifier: License :: OSI Approved :: MIT License
Classifier: Operating System :: Microsoft :: Windows
Classifier: Operating System :: POSIX :: Linux
Project-URL: Homepage, https://alice-lri.github.io/
Project-URL: Documentation, https://alice-lri.github.io/alice-lri/
Project-URL: Repository, https://github.com/alice-lri/alice-lri.git
Project-URL: Issues, https://github.com/alice-lri/alice-lri/issues
Requires-Python: >=3.8
Requires-Dist: numpy>=1.20.0
Provides-Extra: dev
Requires-Dist: pytest>=6.0; extra == "dev"
Requires-Dist: mypy>=0.900; extra == "dev"
Provides-Extra: test
Requires-Dist: pytest>=6.0; extra == "test"
Requires-Dist: numpy>=1.20.0; extra == "test"
